{"name":"Job Title","children":[{"name":"Data Scientist","children":[{"name":"Data Scientist","total":"635"},{"name":"Data Science Manager","total":"59"},{"name":"Principal Data Scientist","total":"9"},{"name":"Staff Data Scientist","total":"2"},{"name":"Data Science Engineer","total":"8"},{"name":"Head of Data Science","total":"11"},{"name":"Managing Director Data Science","total":"1"},{"name":"Data Science Consultant","total":"25"},{"name":"Director of Data Science","total":"19"},{"name":"Data Science Lead","total":"10"},{"name":"Applied Data Scientist","total":"10"},{"name":"Lead Data Scientist","total":"9"},{"name":"Data Science Tech Lead","total":"1"},{"name":"Data Scientist Lead","total":"2"}]},{"name":"Data Engineer","children":[{"name":"Data Engineer","total":"702"},{"name":"Consultant Data Engineer","total":"1"},{"name":"Data Quality Engineer","total":"1"},{"name":"Software Data Engineer","total":"3"},{"name":"Data Engineer 2","total":"1"},{"name":"Cloud Data Engineer","total":"4"},{"name":"Data Operations Engineer","total":"8"},{"name":"Data DevOps Engineer","total":"1"},{"name":"Big Data Engineer","total":"10"},{"name":"BI Data Engineer","total":"1"},{"name":"Cloud Database Engineer","total":"5"},{"name":"Data Infrastructure Engineer","total":"5"},{"name":"Azure Data Engineer","total":"1"},{"name":"Marketing Data Engineer","total":"1"},{"name":"Data Analytics Engineer","total":"5"},{"name":"Lead Data Engineer","total":"6"},{"name":"Principal Data Engineer","total":"2"}]},{"name":"Data Analyst","children":[{"name":"Analytics Engineer","total":"132"},{"name":"Data Analyst","total":"459"},{"name":"BI Analyst","total":"17"},{"name":"Data Analytics Manager","total":"23"},{"name":"Data Quality Analyst","total":"8"},{"name":"Business Intelligence Analyst","total":"6"},{"name":"Research Analyst","total":"5"},{"name":"Business Intelligence Data Analyst","total":"2"},{"name":"Finance Data Analyst","total":"3"},{"name":"Compliance Data Analyst","total":"2"},{"name":"Business Data Analyst","total":"15"},{"name":"Analytics Engineering Manager","total":"1"},{"name":"Insight Analyst","total":"2"},{"name":"Staff Data Analyst","total":"2"},{"name":"Product Data Analyst","total":"6"},{"name":"BI Data Analyst","total":"14"},{"name":"Data Visualization Analyst","total":"2"},{"name":"Sales Data Analyst","total":"1"},{"name":"Data Operations Analyst","total":"6"},{"name":"Lead Data Analyst","total":"5"},{"name":"Financial Data Analyst","total":"3"},{"name":"Data Analytics Specialist","total":"2"},{"name":"Data Analytics Lead","total":"2"},{"name":"Data Analytics Consultant","total":"2"},{"name":"Marketing Data Analyst","total":"2"},{"name":"Principal Data Analyst","total":"2"}]},{"name":"ML Engineer","children":[{"name":"Machine Learning Engineer","total":"300"},{"name":"Machine Learning Software Engineer","total":"13"},{"name":"Machine Learning Scientist","total":"40"},{"name":"ML Engineer","total":"59"},{"name":"Staff Machine Learning Engineer","total":"1"},{"name":"Machine Learning Specialist","total":"2"},{"name":"Principal Machine Learning Engineer","total":"2"},{"name":"MLOps Engineer","total":"6"},{"name":"Lead Machine Learning Engineer","total":"4"},{"name":"Machine Learning Research Engineer","total":"4"},{"name":"Machine Learning Infrastructure Engineer","total":"13"},{"name":"Applied Machine Learning Scientist","total":"13"},{"name":"Machine Learning Developer","total":"8"},{"name":"Applied Machine Learning Engineer","total":"3"},{"name":"Machine Learning Researcher","total":"5"},{"name":"Machine Learning Manager","total":"3"},{"name":"Head of Machine Learning","total":"1"}]},{"name":"Others","children":[{"name":"Business Intelligence Developer","total":"6"},{"name":"Decision Scientist","total":"7"},{"name":"BI Developer","total":"18"},{"name":"Data Manager","total":"35"},{"name":"Business Intelligence Engineer","total":"20"},{"name":"AI Programmer","total":"4"},{"name":"Applied Scientist","total":"49"},{"name":"Research Engineer","total":"57"},{"name":"Research Scientist","total":"104"},{"name":"Data Lead","total":"4"},{"name":"Data Strategist","total":"4"},{"name":"Data Architect","total":"84"},{"name":"AI Architect","total":"4"},{"name":"Computer Vision Engineer","total":"22"},{"name":"Head of Data","total":"15"},{"name":"Deep Learning Engineer","total":"8"},{"name":"Data Visualization Specialist","total":"2"},{"name":"Data Operations Manager","total":"2"},{"name":"Data Specialist","total":"19"},{"name":"AI Scientist","total":"18"},{"name":"Data Modeller","total":"2"},{"name":"Data Operations Specialist","total":"4"},{"name":"ETL Developer","total":"7"},{"name":"NLP Engineer","total":"13"},{"name":"AWS Data Architect","total":"1"},{"name":"Data Integration Specialist","total":"2"},{"name":"Autonomous Vehicle Technician","total":"2"},{"name":"Data Modeler","total":"5"},{"name":"ETL Engineer","total":"2"},{"name":"AI Developer","total":"9"},{"name":"Deep Learning Researcher","total":"1"},{"name":"Big Data Architect","total":"2"},{"name":"Computer Vision Software Engineer","total":"5"},{"name":"Manager Data Management","total":"1"},{"name":"Data Management Specialist","total":"1"},{"name":"Principal Data Architect","total":"1"},{"name":"Cloud Data Architect","total":"1"}]}]}